{
  "em": "emi",
  "emo": "emi",
  "em chestunnav": "emi chestunnav",
  "nv": "nuvvu",
  "nvv": "nuvvu",
  "na": "naaku",
  "naku": "naaku",
  "nee": "neeku",
  "meeru": "meeru",
  "mee": "meeru",
  "vadu": "vaadu",
  "vadu": "vaadu",
  "adi": "adi",
  "ivi": "ivi",
  "anni": "anni",
  "anta": "antaa",
  "ante": "antee",
  "aithe": "ayithe",
  "aythe": "ayithe",
  "cheppu": "cheppu",
  "chepu": "cheppu",
  "chep": "cheppu",
  "chesta": "chestaa",
  "chestha": "chestaa",
  "chestun": "chestunnaa",
  "chestunna": "chestunnaa",
  "chestunnav": "chestunnavu",
  "ledu": "ledu",
  "edu": "ledu",
  "ldu": "ledu",
  "undi": "undi",
  "undu": "undi",
  "unadi": "undhi",
  "undhi": "undhi",
  "paddu": "paddu",
  "padu": "paddu",
  "vstu": "vastu",
  "vastaa": "vastu",
  "vasta": "vastu",
  "pori": "poru",
  "poru": "poru",
  "ra": "raa",
  "raa": "raa",
  "da": "daa",
  "daa": "daa",
  "ba": "baa",
  "lo": "lో",
  "ki": "ki",
  "ku": "ku",
  "tho": "tho",
  "to": "tho",
  "gurinchi": "gurinchi",
  "grnchi": "gurinchi",
  "gurchi": "gurinchi",
  "kadu": "kaadu",
  "kaadu": "kaadu",
  "kda": "kaadu",
  "em": "emi",
  "enni": "enni",
  "eppudu": "eppudu",
  "epudu": "eppudu",
  "epdu": "eppudu",
  "ekkada": "ekkada",
  "ekda": "ekkada",
  "ela": "ela",
  "elaa": "ela",
  "malli": "malli",
  "mari": "maari",
  "maari": "maari",
  "nakku": "naaku",
  "neeku": "neeku",
  "niku": "neeku",
  "kooda": "kooda",
  "kuda": "kooda",
  "kd": "kooda",
  "oka": "oka",
  "okka": "okka",
  "anni": "anni",
  "anni": "anni",
  "baaga": "baaga",
  "baga": "baaga",
  "bagundi": "baagundi",
  "baagundi": "baagundi",
  "chala": "chaala",
  "chaala": "chaala",
  "chla": "chaala",
  "super": "super",
  "sup": "super",
  "superrr": "super",
  "anna": "annaa",
  "annaa": "annaa",
  "akka": "akka",
  "abba": "abba",
  "ayyo": "ayyo",
  "ayyoo": "ayyo",
  "arre": "arre",
  "arrey": "arre",
  "enduku": "enduku",
  "endku": "enduku",
  "endk": "enduku",
  "bokka": "bokka",
  "bkk": "bokka",
  "prathi": "prati",
  "prati": "prati",
  "ila": "ila",
  "ilaa": "ila",
  "ippudu": "ippudu",
  "ipudu": "ippudu",
  "ipdu": "ippudu",
  "tarvata": "taruvata",
  "taruvata": "taruvata",
  "mundhu": "mundu",
  "mundu": "mundu",
  "konchem": "konchem",
  "koncem": "konchem",
  "koncm": "konchem",
  "chinnaga": "chinnaga",
  "chnga": "chinnaga",
  "pa괜찮다": "parvaaledu",
  "parvaaledu": "parvaaledu",
  "parvaledu": "parvaaledu",
  "pvledu": "parvaaledu"
}
